odoo/addons/mrp_subcontracting_partner_management/README.rst
odoo/addons/mrp_subcontracting_partner_management/__init__.py
odoo/addons/mrp_subcontracting_partner_management/__manifest__.py
odoo/addons/mrp_subcontracting_partner_management/i18n/es.po
odoo/addons/mrp_subcontracting_partner_management/i18n/hr.po
odoo/addons/mrp_subcontracting_partner_management/i18n/it.po
odoo/addons/mrp_subcontracting_partner_management/i18n/mrp_subcontracting_partner_management.pot
odoo/addons/mrp_subcontracting_partner_management/models/__init__.py
odoo/addons/mrp_subcontracting_partner_management/models/res_partner.py
odoo/addons/mrp_subcontracting_partner_management/models/stock_picking_type.py
odoo/addons/mrp_subcontracting_partner_management/readme/CONFIGURE.rst
odoo/addons/mrp_subcontracting_partner_management/readme/CONTRIBUTORS.rst
odoo/addons/mrp_subcontracting_partner_management/readme/DESCRIPTION.rst
odoo/addons/mrp_subcontracting_partner_management/readme/HISTORY.rst
odoo/addons/mrp_subcontracting_partner_management/readme/USAGE.rst
odoo/addons/mrp_subcontracting_partner_management/static/description/icon.png
odoo/addons/mrp_subcontracting_partner_management/static/description/index.html
odoo/addons/mrp_subcontracting_partner_management/tests/__init__.py
odoo/addons/mrp_subcontracting_partner_management/tests/test_create_subcontractor_partner_location.py
odoo/addons/mrp_subcontracting_partner_management/views/res_partner_views.xml
odoo/addons/mrp_subcontracting_partner_management/views/stock_picking_type_views.xml
odoo_addon_mrp_subcontracting_partner_management-16.0.1.1.0.2.dist-info/METADATA
odoo_addon_mrp_subcontracting_partner_management-16.0.1.1.0.2.dist-info/WHEEL
odoo_addon_mrp_subcontracting_partner_management-16.0.1.1.0.2.dist-info/top_level.txt
odoo_addon_mrp_subcontracting_partner_management-16.0.1.1.0.2.dist-info/RECORD
