Metadata-Version: 2.1
Name: odoo-addon-mrp_subcontracting_partner_management
Version: 16.0.1.1.0.2
Summary: Subcontracting Partner Management
Home-page: https://github.com/OCA/manufacture
Author: Ooops404, Cetmix, Odoo Community Association (OCA)
Author-email: support@odoo-community.org
License: LGPL-3
Classifier: Programming Language :: Python
Classifier: Framework :: Odoo
Classifier: Framework :: Odoo :: 16.0
Classifier: License :: OSI Approved :: GNU Lesser General Public License v3 (LGPLv3)
Requires-Python: >=3.10
Requires-Dist: odoo <16.1dev,>=16.0a
